mcp_server_duckdb/__init__.py
mcp_server_duckdb/config.py
mcp_server_duckdb/server.py
mseep_mcp_server_duckdb-1.1.4.dist-info/licenses/LICENSE
mseep_mcp_server_duckdb-1.1.4.dist-info/METADATA
mseep_mcp_server_duckdb-1.1.4.dist-info/WHEEL
mseep_mcp_server_duckdb-1.1.4.dist-info/entry_points.txt
mseep_mcp_server_duckdb-1.1.4.dist-info/top_level.txt
mseep_mcp_server_duckdb-1.1.4.dist-info/RECORD
