Metadata-Version: 2.4
Name: mseep-mcp-server-duckdb
Version: 1.1.4
Summary: A DuckDB MCP server
Author-email: mseep <support@skydeck.ai>
License: The MIT License (MIT)
Project-URL: Homepage, https://github.com/ktanaka101/mcp-server-duckdb
Project-URL: Bug Tracker, https://github.com/ktanaka101/mcp-server-duckdb/issues
Classifier: License :: OSI Approved :: MIT License
Classifier: Operating System :: OS Independent
Classifier: Programming Language :: Python :: 3
Classifier: Programming Language :: Python :: 3.10
Classifier: Programming Language :: Python :: 3.11
Classifier: Programming Language :: Python :: 3.12
Classifier: Programming Language :: Python :: 3.13
Classifier: Programming Language :: Python :: 3.14
Requires-Python: >=3.10
License-File: LICENSE
Requires-Dist: duckdb>=1.1.3
Requires-Dist: mcp>=1.0.0
Dynamic: license-file
